segment_anything_hq/__init__.py
segment_anything_hq/automatic_mask_generator.py
segment_anything_hq/build_sam.py
segment_anything_hq/build_sam_baseline.py
segment_anything_hq/predictor.py
segment_anything_hq/modeling/__init__.py
segment_anything_hq/modeling/common.py
segment_anything_hq/modeling/image_encoder.py
segment_anything_hq/modeling/mask_decoder.py
segment_anything_hq/modeling/mask_decoder_hq.py
segment_anything_hq/modeling/prompt_encoder.py
segment_anything_hq/modeling/sam.py
segment_anything_hq/modeling/tiny_vit_sam.py
segment_anything_hq/modeling/transformer.py
segment_anything_hq/utils/__init__.py
segment_anything_hq/utils/amg.py
segment_anything_hq/utils/onnx.py
segment_anything_hq/utils/transforms.py
segment_anything_hq-0.3.dist-info/LICENSE
segment_anything_hq-0.3.dist-info/METADATA
segment_anything_hq-0.3.dist-info/WHEEL
segment_anything_hq-0.3.dist-info/top_level.txt
segment_anything_hq-0.3.dist-info/RECORD
