Metadata-Version: 2.1
Name: segment-anything-hq
Version: 0.3
Summary: Official Python package for Segment Anything in High Quality (https://arxiv.org/abs/2306.01567)
Home-page: https://github.com/SysCV/sam-hq
Author: Mingqiao Ye
Author-email: mingqiaoye@gmail.com
License: MIT license
Classifier: Intended Audience :: Developers
Classifier: License :: OSI Approved :: MIT License
Classifier: Natural Language :: English
Classifier: Programming Language :: Python :: 3.8
Classifier: Programming Language :: Python :: 3.9
Classifier: Programming Language :: Python :: 3.10
Classifier: Programming Language :: Python :: 3.11
Requires-Python: >=3.8
License-File: LICENSE
Requires-Dist: torch (>=1.7)
Requires-Dist: torchvision (>=0.8)
Provides-Extra: all
Requires-Dist: matplotlib ; extra == 'all'
Requires-Dist: pycocotools ; extra == 'all'
Requires-Dist: opencv-python ; extra == 'all'
Requires-Dist: onnx ; extra == 'all'
Requires-Dist: onnxruntime ; extra == 'all'
Provides-Extra: dev
Requires-Dist: flake8 ; extra == 'dev'
Requires-Dist: isort ; extra == 'dev'
Requires-Dist: black ; extra == 'dev'
Requires-Dist: mypy ; extra == 'dev'
